seldonian/__init__.py
seldonian/dataset.py
seldonian/hyperparam_search.py
seldonian/seldonian_algorithm.py
seldonian/spec.py
seldonian/RL/RL_generate_dataset_and_spec_file.py
seldonian/RL/RL_model.py
seldonian/RL/RL_runner.py
seldonian/RL/__init__.py
seldonian/RL/generate_gridworld_episodes.py
seldonian/RL/generate_mountaincar_episodes.py
seldonian/RL/generate_simglucose_episodes.py
seldonian/RL/hyperparams_and_settings.py
seldonian/RL/profiling_seldonian_RL.py
seldonian/RL/Agents/Agent.py
seldonian/RL/Agents/Discrete_Random_Agent.py
seldonian/RL/Agents/Parameterized_non_learning_softmax_agent.py
seldonian/RL/Agents/__init__.py
seldonian/RL/Agents/keyboard_gridworld.py
seldonian/RL/Agents/mountain_car_rough_solution.py
seldonian/RL/Agents/simglucose_custom_fixedarea_random_agent.py
seldonian/RL/Agents/Bases/Fourier.py
seldonian/RL/Agents/Bases/__init__.py
seldonian/RL/Agents/Function_Approximators/Function_Approximator.py
seldonian/RL/Agents/Function_Approximators/Linear_FA.py
seldonian/RL/Agents/Function_Approximators/Table.py
seldonian/RL/Agents/Function_Approximators/__init__.py
seldonian/RL/Agents/Policies/Policy.py
seldonian/RL/Agents/Policies/SimglucosePolicyFixedArea.py
seldonian/RL/Agents/Policies/Softmax.py
seldonian/RL/Agents/Policies/__init__.py
seldonian/RL/Env_Description/Env_Description.py
seldonian/RL/Env_Description/Spaces.py
seldonian/RL/Env_Description/__init__.py
seldonian/RL/environments/Environment.py
seldonian/RL/environments/__init__.py
seldonian/RL/environments/gridworld.py
seldonian/RL/environments/mountaincar.py
seldonian/RL/environments/n_step_mountaincar.py
seldonian/RL/environments/simglucose_custom.py
seldonian/RL/environments/simglucose_env.py
seldonian/candidate_selection/__init__.py
seldonian/candidate_selection/candidate_selection.py
seldonian/models/__init__.py
seldonian/models/custom_text_model.py
seldonian/models/models.py
seldonian/models/objectives.py
seldonian/models/pytorch_cnn.py
seldonian/models/pytorch_model.py
seldonian_engine-0.8.11.dist-info/LICENSE
seldonian_engine-0.8.11.dist-info/METADATA
seldonian_engine-0.8.11.dist-info/WHEEL
seldonian_engine-0.8.11.dist-info/top_level.txt
seldonian_engine-0.8.11.dist-info/RECORD
