Metadata-Version: 2.1
Name: seldonian_engine
Version: 0.8.11
Summary: Core library for Seldonian algorithms
Home-page: 
Author: Austin Hoag
Author-email: austinthomashoag@gmail.com
Project-URL: Bug Tracker, https://github.com/seldonian-framework/Engine/issues
Classifier: Programming Language :: Python :: 3
Classifier: License :: OSI Approved :: BSD License
Classifier: Operating System :: OS Independent
Requires-Python: >=3.8
License-File: LICENSE
Requires-Dist: autograd >=1.4
Requires-Dist: cma >=3.2.2
Requires-Dist: graphviz >=0.19.1
Requires-Dist: matplotlib ==3.5.1
Requires-Dist: numpy >=1.21.4
Requires-Dist: pandas >=1.4.1
Requires-Dist: pytest >=7.0.1
Requires-Dist: scikit-learn >=1.1.1
Requires-Dist: scipy >=1.7.3
Requires-Dist: tqdm >=4.64.0
